README.md
setup.cfg
setup.py
argload/ArgumentLoader.py
argload/__init__.py
argload.egg-info/PKG-INFO
argload.egg-info/SOURCES.txt
argload.egg-info/dependency_links.txt
argload.egg-info/not-zip-safe
argload.egg-info/top_level.txt