Metadata-Version: 1.1
Name: argload
Version: 0.1.2
Summary: Argparse, easy reloading of command line arguments
Home-page: https://github.com/ctallec/argload
Author: Corentin Tallec, Thomas Lucas
Author-email: corentin.tallec@polytechnique.edu
License: MIT
Download-URL: https://github.com/ctallec/argload/archive/0.1.2.tar.gz
Keywords: command-line-parser,hyperparameters
Platform: UNKNOWN
